stegcracker/__init__.py
stegcracker/__main__.py
stegcracker/cracker.py
stegcracker/helpers.py
stegcracker-2.1.0.dist-info/LICENSE.md
stegcracker-2.1.0.dist-info/METADATA
stegcracker-2.1.0.dist-info/WHEEL
stegcracker-2.1.0.dist-info/entry_points.txt
stegcracker-2.1.0.dist-info/top_level.txt
stegcracker-2.1.0.dist-info/RECORD
