Metadata-Version: 2.1
Name: stegcracker
Version: 2.1.0
Summary: Steganography brute-force utility to uncover hidden data inside files.
Home-page: https://github.com/Paradoxis/StegCracker
Author: Luke Paris (Paradoxis)
Author-email: luke@paradoxis.nl
License: MIT
Platform: UNKNOWN
Classifier: License :: OSI Approved :: MIT License
Classifier: Programming Language :: Python
Classifier: Programming Language :: Python :: 3
Classifier: Programming Language :: Python :: 3.6
Classifier: Programming Language :: Python :: Implementation :: CPython
Classifier: Programming Language :: Python :: Implementation :: PyPy
Requires-Python: >=3.6.0
Provides-Extra: test
Provides-Extra: dev
